relaynet_pytorch/__init__.py
relaynet_pytorch/data_utils.py
relaynet_pytorch/relay_net.py
relaynet_pytorch/solver.py
relaynet_pytorch/net_api/__init__.py
relaynet_pytorch/net_api/losses.py
relaynet_pytorch/net_api/sub_module.py
relaynet_pytorch-1.1.dist-info/DESCRIPTION.rst
relaynet_pytorch-1.1.dist-info/METADATA
relaynet_pytorch-1.1.dist-info/RECORD
relaynet_pytorch-1.1.dist-info/WHEEL
relaynet_pytorch-1.1.dist-info/metadata.json
relaynet_pytorch-1.1.dist-info/top_level.txt
